qrpypass/__init__.py
qrpypass/auth/__init__.py
qrpypass/auth/generate.py
qrpypass/auth/models.py
qrpypass/auth/otpauth.py
qrpypass/auth/store.py
qrpypass/auth/totp.py
qrpypass/classify/__init__.py
qrpypass/classify/models.py
qrpypass/classify/payload.py
qrpypass/generate/__init__.py
qrpypass/generate/models.py
qrpypass/generate/payloads.py
qrpypass/qr/__init__.py
qrpypass/qr/decode.py
qrpypass/qr/models.py
qrpypass/qr/pipeline.py
qrpypass/qr/scan.py
qrpypass/service/__init__.py
qrpypass/service/app.py
qrpypass/service/db.py
qrpypass/service/run.py
qrpypass-0.2.3.dist-info/METADATA
qrpypass-0.2.3.dist-info/WHEEL
qrpypass-0.2.3.dist-info/top_level.txt
qrpypass-0.2.3.dist-info/RECORD
