Metadata-Version: 2.4
Name: qrpypass
Version: 0.2.3
Summary: Headless QR decoder + TOTP authenticator Flask mini-service
Author: Josh Gompert
Author-email: 
License: MIT
Project-URL: Homepage, https://ginkorea.one
Project-URL: Repository, https://github.com/ginkorea/qr-pypass
Project-URL: Issues, https://github.com/ginkorea/qr-pypass/issues
Requires-Python: >=3.9
Requires-Dist: Flask>=3.0.0
Requires-Dist: cryptography>=41.0.0
Requires-Dist: Pillow>=10.0.0
Requires-Dist: numpy>=1.23.0
Requires-Dist: qrcode[pil]>=7.4.2
Requires-Dist: opencv-contrib-python-headless>=4.8.0
Requires-Dist: pyzbar>=0.1.9
Requires-Dist: zxing-cpp>=2.2.0
Dynamic: requires-python
